olivaw/__init__.py
olivaw/corese-library-python-4.4.1.jar
olivaw/main.py
olivaw/constants/__init__.py
olivaw/constants/badges.py
olivaw/constants/corese_info.py
olivaw/constants/error-resources.json
olivaw/constants/git_info.py
olivaw/constants/markdown.py
olivaw/constants/olivaw.py
olivaw/constants/paths.py
olivaw/constants/prefixcc.py
olivaw/constants/rdflib_info.py
olivaw/constants/regex.py
olivaw/constants/sparql.py
olivaw/constants/uri_index.json
olivaw/constants/uris.py
olivaw/hook/__init__.py
olivaw/hook/test.py
olivaw/init/__init__.py
olivaw/init/branch.py
olivaw/init/readme.py
olivaw/init/repo.py
olivaw/init/util/__init__.py
olivaw/init/util/badge.py
olivaw/show/__init__.py
olivaw/show/badges.py
olivaw/show/gist.py
olivaw/show/util/__init__.py
olivaw/show/util/badge.py
olivaw/test/__init__.py
olivaw/test/corese.py
olivaw/test/markdown.py
olivaw/test/olivaw.ttl
olivaw/test/turtle.py
olivaw/test/data/__init__.py
olivaw/test/data/suite.py
olivaw/test/data/testing.py
olivaw/test/generic/__init__.py
olivaw/test/generic/namespace.py
olivaw/test/generic/shacl.py
olivaw/test/generic/uri.py
olivaw/test/model/__init__.py
olivaw/test/model/best_practices.py
olivaw/test/model/suite.py
olivaw/test/model/testing.py
olivaw/test/query/__init__.py
olivaw/test/query/suite.py
olivaw/test/query/testing.py
olivaw/test/query/uris.py
olivaw/test/util/__init__.py
olivaw/test/util/draft.py
olivaw/test/util/encoding.py
olivaw/test/util/namespace.py
olivaw/test/util/nlp.py
olivaw/test/util/print.py
olivaw/test/util/skip.py
olivaw-0.0.8.dist-info/licenses/LICENSE
olivaw-0.0.8.dist-info/METADATA
olivaw-0.0.8.dist-info/WHEEL
olivaw-0.0.8.dist-info/entry_points.txt
olivaw-0.0.8.dist-info/top_level.txt
olivaw-0.0.8.dist-info/RECORD
