Metadata-Version: 2.4
Name: olivaw
Version: 0.0.8
Summary: Python framework for supporting agile ontology development
Home-page: https://github.com/Wimmics/olivaw
Download-URL: https://pypi.org/project/olivaw/
Author: Nicolas Robert
Author-email: nicolas.robert@inria.fr
Maintainer: Nicolas Robert
Maintainer-email: nicolas.robert@inria.fr
License: LGPL-2.1
Keywords: semantics,ontology,schema,vocabulary,linked data,validation,RDF,RDFS,OWL,SHACL,SPARQL
Requires-Python: >=3.10
License-File: LICENSE
Requires-Dist: py4j==0.10.9.7
Requires-Dist: rdflib==6.3.2
Requires-Dist: regex==2023.8.8
Requires-Dist: requests==2.31.0
Requires-Dist: python-dotenv==1.0.0
Requires-Dist: tqdm==4.66.1
Dynamic: author
Dynamic: author-email
Dynamic: description
Dynamic: description-content-type
Dynamic: download-url
Dynamic: home-page
Dynamic: keywords
Dynamic: license
Dynamic: license-file
Dynamic: maintainer
Dynamic: maintainer-email
Dynamic: requires-dist
Dynamic: requires-python
Dynamic: summary
